pydantic_mermaid/__init__.py
pydantic_mermaid/__main__.py
pydantic_mermaid/mermaid_generator.py
pydantic_mermaid/models.py
pydantic_mermaid/py.typed
pydantic_mermaid/pydantic_parser.py
pydantic_mermaid/template.j2
pydantic_mermaid-0.7.1.dist-info/LICENSE
pydantic_mermaid-0.7.1.dist-info/METADATA
pydantic_mermaid-0.7.1.dist-info/WHEEL
pydantic_mermaid-0.7.1.dist-info/entry_points.txt
pydantic_mermaid-0.7.1.dist-info/RECORD
