Metadata-Version: 2.1
Name: pydantic-mermaid
Version: 0.7.1
Summary: Convert pydantic 1.9 classes to markdown mermaid class charts
Home-page: https://github.com/EricWebsmith/pydantic_mermaid
Author: Eric Websmith
Author-email: eric.websmith@gmail.com
Requires-Python: >=3.8,<4.0
Classifier: License :: OSI Approved :: MIT License
Classifier: Operating System :: OS Independent
Classifier: Programming Language :: Python :: 3
Classifier: Programming Language :: Python :: 3.8
Classifier: Programming Language :: Python :: 3.9
Classifier: Programming Language :: Python :: 3.10
Classifier: Programming Language :: Python :: 3.11
Classifier: Programming Language :: Python :: 3.12
Requires-Dist: importlib-resources (>=6.1.1,<7.0.0)
Requires-Dist: jinja2 (>=3.1.3,<4.0.0)
Requires-Dist: pydantic (>=1.9,<2.0)
